piva/__init__.py
piva/cmaps.py
piva/config.py
piva/constants.py
piva/data_browser.py
piva/data_loaders.py
piva/data_viewer_2d.py
piva/data_viewer_3d.py
piva/data_viewer_4d.py
piva/fitters.py
piva/image_panels.py
piva/main.py
piva/plot_tool.py
piva/qcheckcombobox.py
piva/utilities_panel.py
piva/working_procedures.py
piva/ipynb_templates/template-metadata.ipynb
piva/ipynb_templates/template.ipynb
piva/tests/__init__.py
piva/tests/dataloaders_test.py
piva/tests/jupyter_test.py
piva/tests/viewers_test.py
piva/tests/wp_test.py
piva/tests/data/als-hers-cut.pxt
piva/tests/data/als-merlin-cut.h5
piva/tests/data/als-merlin-light_map.ibw
piva/tests/data/cassiopee-cut1.pxt
piva/tests/data/cassiopee-cut1.txt
piva/tests/data/diamond-i05-bmap_new.nxs
piva/tests/data/maxiv-bloch-cut.ibw
piva/tests/data/maxiv-bloch-cut.pxt
piva/tests/data/maxiv-bloch-cut.zip
piva/tests/data/pickle-cut.p
piva/tests/data/pickle-raster.p
piva/tests/data/sls-adress-cut.h5
piva/tests/data/sls-sis-cut.h5
piva/tests/data/sls-sis-cut.ibw
piva/tests/data/sls-sis-cut.pxt
piva/tests/data/sls-sis-map.h5
piva/tests/data/solaris-uranos-cut.ibw
piva/tests/data/solaris-uranos-cut.pxt
piva/tests/data/test_map.p
piva/tests/data/wp_test_data.p
piva/tests/data/cassiopee-rmap/note.txt
piva/tests/data/cassiopee-rmap/rmap_90eV_10_ROI1_.txt
piva/tests/data/cassiopee-rmap/rmap_90eV_10_i.txt
piva/tests/data/cassiopee-rmap/rmap_90eV_11_ROI1_.txt
piva/tests/data/cassiopee-rmap/rmap_90eV_11_i.txt
piva/tests/data/cassiopee-rmap/rmap_90eV_12_ROI1_.txt
piva/tests/data/cassiopee-rmap/rmap_90eV_12_i.txt
piva/tests/data/cassiopee-rmap/rmap_90eV_13_ROI1_.txt
piva/tests/data/cassiopee-rmap/rmap_90eV_13_i.txt
piva/tests/data/cassiopee-rmap/rmap_90eV_14_ROI1_.txt
piva/tests/data/cassiopee-rmap/rmap_90eV_14_i.txt
piva/tests/data/cassiopee-rmap/rmap_90eV_15_ROI1_.txt
piva/tests/data/cassiopee-rmap/rmap_90eV_15_i.txt
piva/tests/data/cassiopee-rmap/rmap_90eV_16_ROI1_.txt
piva/tests/data/cassiopee-rmap/rmap_90eV_16_i.txt
piva-3.0.0.dist-info/METADATA
piva-3.0.0.dist-info/WHEEL
piva-3.0.0.dist-info/entry_points.txt
piva-3.0.0.dist-info/licenses/LICENSE
piva-3.0.0.dist-info/RECORD
