Metadata-Version: 2.4
Name: piva
Version: 3.0.0
Summary: PIVA - Photoemission Interface for Visualization and Analysis
Project-URL: Homepage, https://github.com/pudeIko/piva.git
Project-URL: Documentation, https://piva.readthedocs.io/en/latest/intro.html
Author-email: Wojtek Pudelko <wojciech.pudelko@psi.ch>
License-Expression: MIT
License-File: LICENSE
Classifier: License :: OSI Approved :: MIT License
Classifier: Operating System :: OS Independent
Classifier: Programming Language :: Python :: 3
Requires-Python: >=3.10
Requires-Dist: data-slicer>=1.0.2
Requires-Dist: h5py>=3.11.0
Requires-Dist: igor2>=0.5
Requires-Dist: ipywidgets>=7.6.3
Requires-Dist: julia>=0.5.6
Requires-Dist: jupyterlab>=3.5
Requires-Dist: jupyterthemes>=0.20.0
Requires-Dist: matplotlib>=3.3.4
Requires-Dist: numba>=0.57.0
Requires-Dist: numpy<2.0.0
Requires-Dist: openpyxl>=3.0.9
Requires-Dist: pandas>=1.3.5
Requires-Dist: pydantic>=2.0.0
Requires-Dist: pyqt5>=5.15.0
Requires-Dist: pyqtgraph>=0.13.1
Requires-Dist: scipy>=1.6.0
Requires-Dist: tqdm>=4.56.0
Requires-Dist: typing>=3.7
Provides-Extra: test
Requires-Dist: pytest; extra == 'test'
Requires-Dist: tox; extra == 'test'
